<?xml version="1.0" encoding="utf-8" ?>
<dwsync>
<file name="icon-checklist.png" server="sftp.itd.umich.edu//afs/umich.edu/group/i/itsweb/" local="131243942000000000" remote="131243942000000000" Dst="1" />
<file name="icon-exclamation.png" server="sftp.itd.umich.edu//afs/umich.edu/group/i/itsweb/" local="131243942000000000" remote="131243942000000000" Dst="1" />
<file name="icon-lock.png" server="sftp.itd.umich.edu//afs/umich.edu/group/i/itsweb/" local="131243942000000000" remote="131243942000000000" Dst="1" />
<file name="icon-magnify.png" server="sftp.itd.umich.edu//afs/umich.edu/group/i/itsweb/" local="131243942000000000" remote="131243942000000000" Dst="1" />
<file name="icon-pencil.png" server="sftp.itd.umich.edu//afs/umich.edu/group/i/itsweb/" local="131243942000000000" remote="131243942000000000" Dst="1" />
<file name="icon-thumbsup.png" server="sftp.itd.umich.edu//afs/umich.edu/group/i/itsweb/" local="131243942000000000" remote="131243942000000000" Dst="1" />
<file name="iia-wordmark-72-white.png" server="sftp.itd.umich.edu//afs/umich.edu/group/i/itsweb/" local="131243942000000000" remote="131243942000000000" Dst="1" />
<file name="newsletter-good-for-u-201509.jpg" server="sftp.itd.umich.edu//afs/umich.edu/group/i/itsweb/" local="131243942000000000" remote="131243942000000000" Dst="1" />
<file name="newsletter-infographic-201509.jpg" server="sftp.itd.umich.edu//afs/umich.edu/group/i/itsweb/" local="131243942000000000" remote="131243942000000000" Dst="1" />
<file name="um-logo-m36.png" server="sftp.itd.umich.edu//afs/umich.edu/group/i/itsweb/" local="131243942000000000" remote="131243942000000000" Dst="1" />
<file name="um-logo-m72.png" server="sftp.itd.umich.edu//afs/umich.edu/group/i/itsweb/" local="131243942000000000" remote="131243942000000000" Dst="1" />
</dwsync>