<?xml version="1.0" encoding="utf-8" ?>
<dwsync>
<file name="201611-miworkspace-qa-team.jpg" server="sftp.itd.umich.edu//afs/umich.edu/group/i/itsweb/" local="131250077580000000" remote="131250077580000000" Dst="1" />
<file name="support-services-updates-email-banner.jpg" server="sftp.itd.umich.edu//afs/umich.edu/group/i/itsweb/" local="131323513930000000" remote="131323513930000000" Dst="1" />
<file name="um-logo-m36.png" server="sftp.itd.umich.edu//afs/umich.edu/group/i/itsweb/" local="131086689350000000" remote="131086689350000000" Dst="1" />
<file name="201611-ctools-migration.jpg" server="sftp.itd.umich.edu//afs/umich.edu/group/i/itsweb/" local="131250077140000000" remote="131250077140000000" Dst="1" />
<file name="201611.html" server="sftp.itd.umich.edu//afs/umich.edu/group/i/itsweb/" local="131250942340000000" remote="131250942340000000" Dst="1" />
<file name="201611-service-center-video.jpg" server="sftp.itd.umich.edu//afs/umich.edu/group/i/itsweb/" local="131251746680000000" remote="131251746680000000" Dst="1" />
<file name="201611-ross-academic-building.jpg" server="sftp.itd.umich.edu//afs/umich.edu/group/i/itsweb/" local="131250076840000000" remote="131250076840000000" Dst="1" />
<file name="201611-service-excellence-logo.png" server="sftp.itd.umich.edu//afs/umich.edu/group/i/itsweb/" local="131250076480000000" remote="131250076480000000" Dst="1" />
<file name="201612.html" server="sftp.itd.umich.edu//afs/umich.edu/group/i/itsweb/" local="131266470860000000" remote="131266470860000000" Dst="1" />
<file name="index.php" server="sftp.itd.umich.edu//afs/umich.edu/group/i/itsweb/" local="131251751870000000" remote="131251751870000000" Dst="1" />
<file name="201612-top-operational-projects.jpg" server="sftp.itd.umich.edu//afs/umich.edu/group/i/itsweb/" local="131263138940000000" remote="131263138940000000" Dst="1" />
<file name="201612-service-center-video.jpg" server="sftp.itd.umich.edu//afs/umich.edu/group/i/itsweb/" local="131263139810000000" remote="131263139810000000" Dst="1" />
<file name="201702-service-excellence-video.jpg" server="sftp.itd.umich.edu//afs/umich.edu/group/i/itsweb/" local="131297707070000000" remote="131297707070000000" Dst="1" />
<file name="201702.html" server="sftp.itd.umich.edu//afs/umich.edu/group/i/itsweb/" local="131324193180000000" remote="131324193180000000" Dst="1" />
<file name="201702-servicenow-helsinki.jpg" server="sftp.itd.umich.edu//afs/umich.edu/group/i/itsweb/" local="131297712550000000" remote="131297712550000000" Dst="1" />
<file name="201702-depot-dashboard.png" server="sftp.itd.umich.edu//afs/umich.edu/group/i/itsweb/" local="131298417800000000" remote="131298417800000000" Dst="1" />
<file name="201701.html" server="sftp.itd.umich.edu//afs/umich.edu/group/i/itsweb/" local="131323418220000000" remote="131323418220000000" Dst="1" />
<file name="201701-depot-dashboard.png" server="sftp.itd.umich.edu//afs/umich.edu/group/i/itsweb/" local="131298417800000000" remote="131298417800000000" Dst="1" />
<file name="201701-servicenow-helsinki.jpg" server="sftp.itd.umich.edu//afs/umich.edu/group/i/itsweb/" local="131297712550000000" remote="131297712550000000" Dst="1" />
<file name="201701-service-excellence-video.jpg" server="sftp.itd.umich.edu//afs/umich.edu/group/i/itsweb/" local="131297707070000000" remote="131297707070000000" Dst="1" />
<file name="201702-service-excellence-logo.png" server="sftp.itd.umich.edu//afs/umich.edu/group/i/itsweb/" local="131250076480000000" remote="131250076480000000" Dst="1" />
<file name="201702-badge-coach.png" server="sftp.itd.umich.edu//afs/umich.edu/group/i/itsweb/" local="131323425420000000" remote="131323425420000000" Dst="1" />
<file name="201702-badge-all-american.png" server="sftp.itd.umich.edu//afs/umich.edu/group/i/itsweb/" local="131323425360000000" remote="131323425360000000" Dst="1" />
<file name="201702-badge-starter.png" server="sftp.itd.umich.edu//afs/umich.edu/group/i/itsweb/" local="131323425320000000" remote="131323425320000000" Dst="1" />
<file name="201702-badge-recruit.png" server="sftp.itd.umich.edu//afs/umich.edu/group/i/itsweb/" local="131323425210000000" remote="131323425210000000" Dst="1" />
<file name="201702-showcase-kissoff.jpg" server="sftp.itd.umich.edu//afs/umich.edu/group/i/itsweb/" local="131323433810000000" remote="131323433810000000" Dst="1" />
<file name="201702-oculus-rift.jpg" server="sftp.itd.umich.edu//afs/umich.edu/group/i/itsweb/" local="131323435820000000" remote="131323435820000000" Dst="1" />
<file name="201703.html" server="sftp.itd.umich.edu//afs/umich.edu/group/i/itsweb/" local="131351092400000000" remote="131351092400000000" Dst="1" />
<file name="201704.html" server="sftp.itd.umich.edu//afs/umich.edu/group/i/itsweb/" local="131376111410000000" remote="131376111410000000" Dst="1" />
<file name="201705.html" server="sftp.itd.umich.edu//afs/umich.edu/group/i/itsweb/" local="131399378230000000" remote="131399378230000000" Dst="1" />
<file name="201705-service-excellence-logo.png" server="sftp.itd.umich.edu//afs/umich.edu/group/i/itsweb/" local="131396899560000000" remote="131396899560000000" Dst="1" />
<file name="201705-park-cleanup.jpg" server="sftp.itd.umich.edu//afs/umich.edu/group/i/itsweb/" local="131396905820000000" remote="131396905820000000" Dst="1" />
<file name="201705-appreciation-day.jpg" server="sftp.itd.umich.edu//afs/umich.edu/group/i/itsweb/" local="131396909320000000" remote="131396909320000000" Dst="1" />
<file name="201707.html" server="sftp.itd.umich.edu//afs/umich.edu/group/i/itsweb/" local="131455600050000000" remote="131455600050000000" Dst="1" />
<file name="201706.html" server="sftp.itd.umich.edu//afs/umich.edu/group/i/itsweb/" local="131433040790000000" remote="131433040790000000" Dst="1" />
<file name="our-focus-is-u-email-banner.jpg" server="sftp.itd.umich.edu//afs/umich.edu/group/i/itsweb/" local="131423696650000000" remote="131423696650000000" Dst="1" />
<file name="201706-service-excellence.jpg" server="sftp.itd.umich.edu//afs/umich.edu/group/i/itsweb/" local="131429766770000000" remote="131429766770000000" Dst="1" />
<file name="201706-8-wastes.jpg" server="sftp.itd.umich.edu//afs/umich.edu/group/i/itsweb/" local="131429770620000000" remote="131429770620000000" Dst="1" />
<file name="201707-team-huddle.jpg" server="sftp.itd.umich.edu//afs/umich.edu/group/i/itsweb/" local="131453944640000000" remote="131453944640000000" Dst="1" />
<file name="201707-team-depot-broomball.jpg" server="sftp.itd.umich.edu//afs/umich.edu/group/i/itsweb/" local="131453944260000000" remote="131453944260000000" Dst="1" />
</dwsync>